qc2tsv/__init__.py
qc2tsv/__main__.py
qc2tsv/cli.py
qc2tsv/qc2tsv.py
qc2tsv-0.2.0.data/scripts/qc2tsv
qc2tsv-0.2.0.dist-info/LICENSE
qc2tsv-0.2.0.dist-info/METADATA
qc2tsv-0.2.0.dist-info/WHEEL
qc2tsv-0.2.0.dist-info/top_level.txt
qc2tsv-0.2.0.dist-info/RECORD
