Metadata-Version: 2.1
Name: qc2tsv
Version: 0.2.0
Summary: Converts multiple QC JSONs to a spread sheet (TSV/CSV)
Home-page: https://github.com/ENCODE-DCC/qc2tsv
Author: Jin Lee
Author-email: leepc12@gmail.com
License: UNKNOWN
Platform: UNKNOWN
Classifier: Programming Language :: Python :: 3
Classifier: License :: OSI Approved :: MIT License
Classifier: Operating System :: POSIX :: Linux
Requires-Python: >=3.6
Requires-Dist: autouri (>=0.1.2.1)
Requires-Dist: pandas (>=1.0.0)
Requires-Dist: caper
